{"metadata": {"dbt_schema_version": "https://schemas.getdbt.com/dbt/run-results/v5.json", "dbt_version": "1.7.10", "generated_at": "2024-03-23T21:15:41.106499Z", "invocation_id": "8557d621-5ed7-4bbf-bc5c-3e35957a1db4", "env": {}}, "results": [{"status": "success", "timing": [{"name": "compile", "started_at": "2024-03-23T21:15:31.788021Z", "completed_at": "2024-03-23T21:15:31.826291Z"}, {"name": "execute", "started_at": "2024-03-23T21:15:31.877963Z", "completed_at": "2024-03-23T21:15:36.182249Z"}], "thread_id": "Thread-2", "execution_time": 4.439317226409912, "adapter_response": {"_message": "CREATE TABLE (1.0k rows, 42.8 KiB processed)", "code": "CREATE TABLE", "rows_affected": 1000, "bytes_processed": 43792, "bytes_billed": 10485760, "location": "US", "project_id": "hive-413217", "job_id": "38993d2e-2526-465f-9d5f-2f8167a2c221", "slot_ms": 8126}, "message": "CREATE TABLE (1.0k rows, 42.8 KiB processed)", "failures": null, "unique_id": "model.retail.store", "compiled": true, "compiled_code": "\n\nwith base as (\n    SELECT\n        store_id,\n        location,\n        size,\n        manager\n    FROM\n       `hive-413217`.`retail_2`.`store`\n)\n\nSELECT\n    *\nFROM\n    base", "relation_name": "`hive-413217`.`dbt_retail`.`store`"}, {"status": "success", "timing": [{"name": "compile", "started_at": "2024-03-23T21:15:31.770351Z", "completed_at": "2024-03-23T21:15:31.818008Z"}, {"name": "execute", "started_at": "2024-03-23T21:15:31.834116Z", "completed_at": "2024-03-23T21:15:36.185548Z"}], "thread_id": "Thread-1", "execution_time": 4.448373317718506, "adapter_response": {"_message": "CREATE TABLE (2.0k rows, 103.1 KiB processed)", "code": "CREATE TABLE", "rows_affected": 2000, "bytes_processed": 105625, "bytes_billed": 10485760, "location": "US", "project_id": "hive-413217", "job_id": "5bde21c1-33ec-4ccf-945a-26cd91d8a60a", "slot_ms": 6044}, "message": "CREATE TABLE (2.0k rows, 103.1 KiB processed)", "failures": null, "unique_id": "model.retail.product", "compiled": true, "compiled_code": "\n\nwith base as (\n    SELECT\n        product_id,\n        name,\n        category,\n        base_price,\n        supplier_id\n    FROM\n       `hive-413217`.`retail_2`.`product`\n)\n\nSELECT\n    *\nFROM\n    base", "relation_name": "`hive-413217`.`dbt_retail`.`product`"}, {"status": "success", "timing": [{"name": "compile", "started_at": "2024-03-23T21:15:31.795389Z", "completed_at": "2024-03-23T21:15:31.821703Z"}, {"name": "execute", "started_at": "2024-03-23T21:15:31.870417Z", "completed_at": "2024-03-23T21:15:36.967728Z"}], "thread_id": "Thread-3", "execution_time": 5.217541456222534, "adapter_response": {"_message": "CREATE TABLE (88.5k rows, 3.9 MiB processed)", "code": "CREATE TABLE", "rows_affected": 88524, "bytes_processed": 4129614, "bytes_billed": 10485760, "location": "US", "project_id": "hive-413217", "job_id": "9dd196da-7d20-45bc-a42f-e0416c4a68e2", "slot_ms": 10097}, "message": "CREATE TABLE (88.5k rows, 3.9 MiB processed)", "failures": null, "unique_id": "model.retail.transactions", "compiled": true, "compiled_code": "\n\nwith base as (\n    SELECT\n        transaction_id,\n        product_id,\n        timestamp,\n        quantity,\n        unit_price,\n        store_id\n    from\n        `hive-413217`.`retail_2`.`transactions`\n)\n\nSELECT\n    *\nFROM\n    base", "relation_name": "`hive-413217`.`dbt_retail`.`transactions`"}, {"status": "success", "timing": [{"name": "compile", "started_at": "2024-03-23T21:15:36.993968Z", "completed_at": "2024-03-23T21:15:37.009619Z"}, {"name": "execute", "started_at": "2024-03-23T21:15:37.015455Z", "completed_at": "2024-03-23T21:15:41.036257Z"}], "thread_id": "Thread-4", "execution_time": 4.05328106880188, "adapter_response": {"_message": "SCRIPT (0 processed)", "code": "SCRIPT", "bytes_processed": 0, "bytes_billed": 0, "location": "US", "project_id": "hive-413217", "job_id": "35d9e0a3-ab89-4ba3-a922-e964c85ee706", "slot_ms": 0}, "message": "SCRIPT (0 processed)", "failures": null, "unique_id": "model.retail.mv_retail_transactions", "compiled": true, "compiled_code": "\n\nwith cte as (\n  select\n    transaction_id,\n    quantity,\n    unit_price,\n    timestamp,\n    name,\n    category,\n    location,\n    size,\n    manager\n  from\n   `hive-413217`.`dbt_retail`.`transactions` t join `hive-413217`.`dbt_retail`.`product` p on t.product_id = p.product_id\n   join `hive-413217`.`dbt_retail`.`store` s on t.store_id = s.store_id\n)\n\nselect\n *\nfrom\n cte", "relation_name": "`hive-413217`.`dbt_retail`.`mv_retail_transactions`"}], "elapsed_time": 11.422660827636719, "args": {"invocation_command": "dbt build --full-refresh", "log_level": "info", "use_colors": true, "introspect": true, "log_file_max_bytes": 10485760, "populate_cache": true, "warn_error_options": {"include": [], "exclude": []}, "partial_parse": true, "log_format_file": "debug", "defer": false, "strict_mode": false, "indirect_selection": "eager", "select": [], "quiet": false, "full_refresh": true, "log_format": "default", "resource_types": [], "send_anonymous_usage_stats": true, "show": false, "cache_selected_only": false, "favor_state": false, "log_path": "/opt/airflow/dags/dbt/retail/logs", "printer_width": 80, "vars": {}, "project_dir": "/opt/airflow/dags/dbt/retail", "static_parser": true, "partial_parse_file_diff": true, "enable_legacy_logger": false, "write_json": true, "which": "build", "use_colors_file": true, "show_resource_report": false, "macro_debugging": false, "log_level_file": "debug", "include_saved_query": false, "print": true, "profiles_dir": "/opt/airflow/dags/dbt/retail", "version_check": true, "exclude": []}}